clearpasspy.py
clearpasspy-1.1.3.dist-info/LICENSE.md
clearpasspy-1.1.3.dist-info/LICENSE.txt
clearpasspy-1.1.3.dist-info/METADATA
clearpasspy-1.1.3.dist-info/WHEEL
clearpasspy-1.1.3.dist-info/top_level.txt
clearpasspy-1.1.3.dist-info/RECORD
