Metadata-Version: 2.1
Name: clearpasspy
Version: 1.1.3
Summary: ClearPass API Python Library
Home-page: https://github.com/zemerick1/clearpasspy
Author: zemerick1
Author-email: zemerick@emerickcc.com
License: UNKNOWN
Platform: UNKNOWN
Classifier: Programming Language :: Python :: 3
Classifier: License :: OSI Approved :: MIT License
Classifier: Operating System :: OS Independent
Requires-Dist: requests (==2.21.0)
